niceml/__init__.py
niceml/cli/__init__.py
niceml/cli/clicommands.py
niceml/cli/climain.py
niceml/config/__init__.py
niceml/config/configschemas.py
niceml/config/defaultremoveconfigkeys.py
niceml/config/envconfig.py
niceml/config/hydra.py
niceml/config/subsetnames.py
niceml/config/trainparams.py
niceml/config/writeopconfig.py
niceml/dagster/__init__.py
niceml/dagster/jobs/__init__.py
niceml/dagster/jobs/jobs.py
niceml/dagster/jobs/repository.py
niceml/dagster/ops/__init__.py
niceml/dagster/ops/analysis.py
niceml/dagster/ops/copyexp.py
niceml/dagster/ops/cropnumbers.py
niceml/dagster/ops/datageneration.py
niceml/dagster/ops/dfnormalization.py
niceml/dagster/ops/evalcopyexp.py
niceml/dagster/ops/experiment.py
niceml/dagster/ops/exptests.py
niceml/dagster/ops/filelockops.py
niceml/dagster/ops/imagetotable.py
niceml/dagster/ops/localizeexperiment.py
niceml/dagster/ops/prediction.py
niceml/dagster/ops/splitdata.py
niceml/dagster/ops/train.py
niceml/dagster/resources/__init__.py
niceml/dagster/resources/locations.py
niceml/dashboard/__init__.py
niceml/dashboard/binprobvisu.py
niceml/dashboard/components/__init__.py
niceml/dashboard/components/downloadexpviscomponent.py
niceml/dashboard/components/expviscomponent.py
niceml/dashboard/components/linearviscomponent.py
niceml/dashboard/components/metaviscomponent.py
niceml/dashboard/components/prefixviscomponent.py
niceml/dashboard/components/selectionviscomponent.py
niceml/dashboard/configviscomponent.py
niceml/dashboard/dashboard.py
niceml/dashboard/expvisuhelper.py
niceml/dashboard/imagenetdataloggerviscomponent.py
niceml/dashboard/metricviscomponent.py
niceml/dashboard/netdataloggerviscomponent.py
niceml/dashboard/remotettrainutils.py
niceml/dashboard/visualizers/__init__.py
niceml/dashboard/visualizers/boundingboxvisualizer.py
niceml/dashboard/visualizers/imagevisualizer.py
niceml/dashboard/visualizers/maskvisualizer.py
niceml/data/__init__.py
niceml/data/augmentation/__init__.py
niceml/data/augmentation/augmentation.py
niceml-0.16.0.dist-info/LICENSE
niceml-0.16.0.dist-info/METADATA
niceml-0.16.0.dist-info/WHEEL
niceml-0.16.0.dist-info/entry_points.txt
niceml-0.16.0.dist-info/RECORD
