Metadata-Version: 2.1
Name: niceml
Version: 0.16.0
Summary: Welcome to niceML 🍦, a Python-based MLOps framework that uses TensorFlow and Dagster. This framework streamlines the development, and maintenance of machine learning models, providing an end-to-end solution for building efficient and scalable pipelines.
Keywords: tensorflow,scikit-learn,streamlit
Author: Denis Stalz-John
Author-email: denis.stalz-john@codecentric.de
Requires-Python: >=3.9, !=2.7.*, !=3.0.*, !=3.1.*, !=3.2.*, !=3.3.*, !=3.4.*, !=3.5.*, !=3.6.*, !=3.7.*, !=3.8.*, !=3.12.*
Classifier: Development Status :: 3 - Alpha
Classifier: Intended Audience :: Developers
Classifier: License :: OSI Approved :: MIT License
Classifier: Natural Language :: English
Classifier: Operating System :: MacOS
Classifier: Operating System :: POSIX :: Linux
Classifier: Programming Language :: Python
Classifier: Programming Language :: Python :: 3
Classifier: Programming Language :: Python :: 3.9
Classifier: Programming Language :: Python :: 3.10
Classifier: Programming Language :: Python :: 3.11
Classifier: Programming Language :: Python :: 3 :: Only
Classifier: Topic :: Software Development
Classifier: Topic :: Software Development :: Libraries
Classifier: Topic :: Software Development :: Libraries :: Python Modules
Classifier: Typing :: Typed
Provides-Extra: tensorflow
Provides-Extra: tensorflow-macos
Provides-Extra: visu
Requires-Dist: albumentations (>=1.3.0,<2.0.0)
Requires-Dist: altair (>=5.2.0,<6.0.0) ; extra == "visu"
Requires-Dist: cattrs (>=22.2.0,<23.0.0)
Requires-Dist: click (>=8.1.3,<9.0.0)
Requires-Dist: copier (>=7.2.0,<8.0.0)
Requires-Dist: cryptography (>=41.0.0,<42.0.0)
Requires-Dist: cython (>=0.29.34,<0.30.0)
Requires-Dist: dagit (>=1.3.3,<2.0.0)
Requires-Dist: dagster (>=1.6.0,<1.7.0)
Requires-Dist: dagster-mlflow (>=0.22.0,<0.23.0)
Requires-Dist: fastparquet (>=2023.2.0,<2024.0.0)
Requires-Dist: grpcio (>=1.60.0,<2.0.0)
Requires-Dist: hydra-core (>=1.3.2,<2.0.0)
Requires-Dist: invoke (>=1.4.1,<2)
Requires-Dist: isodate (>=0.6.1,<0.7.0)
Requires-Dist: mkdocs-gen-files (>=0.5.0,<0.6.0)
Requires-Dist: networkx (>=3.1,<4.0)
Requires-Dist: opencv-python (>=4.7.0.72,<5.0.0.0)
Requires-Dist: pandas (==1.5.0)
Requires-Dist: pandera (>=0.14.5,<0.15.0)
Requires-Dist: pendulum (>=2.0,<3.0)
Requires-Dist: pillow (>=10.1.0,<11.0.0)
Requires-Dist: protobuf (>=3.0.0,<4.0.0)
Requires-Dist: pympler (>=1.0.1,<2.0.0)
Requires-Dist: python-dotenv (>=1.0.0,<2.0.0)
Requires-Dist: pyyaml (>=6.0,<7.0)
Requires-Dist: requests (>=2.31.0,<3.0.0)
Requires-Dist: schema (>=0.7.5,<0.8.0)
Requires-Dist: scikit-learn (>=1.2.2,<2.0.0)
Requires-Dist: scipy (>=1.8)
Requires-Dist: streamlit (>=1.28.0,<2.0.0) ; extra == "visu"
Requires-Dist: tensorflow (>=2.13,<=2.15) ; extra == "tensorflow"
Requires-Dist: tensorflow-io-gcs-filesystem (==0.34.0) ; extra == "tensorflow" or extra == "tensorflow-macos"
Requires-Dist: tensorflow-macos (>=2.13,<=2.14) ; extra == "tensorflow-macos"
Requires-Dist: tensorflow-metal (>=1.0.0,<2.0.0) ; extra == "tensorflow-macos"
Requires-Dist: toml (>=0.10.2,<0.11.0)
Requires-Dist: tornado (>=6.3.2,<7.0.0)
Project-URL: homepage, https://niceml.io
Project-URL: repository, https://github.com/codecentric-oss/niceml
